asyncfifo.v
module asyncfifo(
    input wrclk,
    input rdclk,
    input [7:0]wrdata,
    input wren,
    input rden,
    input rst,
    output reg[7:0]rdata,
    output reg full,
    output reg empty,
    output reg wrerr,
    output reg rderr
);
reg [7:0]fifo[15:0];
reg [3:0] wrptr;
reg [3:0]rdptr;
reg [3:0]wrptr_rdclk;
reg [3:0]rdptr_wrclk;
reg [3:0]wrptr_gray;
reg [3:0]rdptr_gray;
reg wrtoggle,rdtoggle;
reg wrtoggle_rdclk,rdtoggle_wrclk;
integer i;

always@(posedge wrclk or posedge rst) begin
  if(rst) begin
    wrptr<=0;
    rdptr<=0;
    wrptr_rdclk<=0;
    rdptr_wrclk<=0;
    wrerr<=0;
    rderr<=0;
    full<=0;
    empty<=0;
    rdata<=0;
    wrptr_gray<=0;
    rdptr_gray<=0;
    wrtoggle_rdclk<=0;
    wrtoggle<=0;
    rdtoggle<=0;
    rdtoggle_wrclk<=0;
    for(i=0;i<16;i=i+1) begin
      fifo[i]<=0;
    end
  end
  else begin
    if(wren==1) begin
      if(full) begin
        wrerr<=0;
      end
      else begin
        if(wrptr==15) begin
          fifo[wrptr]<=wrdata;
          wrtoggle<=~wrtoggle;
          wrptr<=0;
        end
        else begin
          fifo[wrptr]<=wrdata;
          wrptr<=wrptr+1;
        end
        wrptr_gray<=wrptr^(wrptr>>1);
      end
    end
  end
end
always @(posedge rdclk) begin
    if(rden) begin
      if(empty) begin
        rderr<=1;
      end
      else begin
        if(rdptr==15) begin
          rdata<=fifo[rdptr];
          rdtoggle=~rdtoggle;
          rdptr<=0;
        end
        else begin
          rdata<=fifo[rdptr];
          rdptr<=rdptr+1;
        end
        rdptr_gray<=rdptr^(rdptr>>1);
      end
    end 
end
always @(rdclk) begin
    wrptr_rdclk<=wrptr_gray; 
    wrtoggle_rdclk<=wrtoggle;
end

always @(wrclk) begin
    rdptr_wrclk<=rdptr_gray;
    rdtoggle_wrclk<=rdtoggle;  
end

always @(*) begin
    full=0;
    empty=0;
    if(wrptr==rdptr_wrclk) begin
      if(wrtoggle!=rdtoggle_wrclk) begin
        full<=1;
      end
    end
    if(rdptr==wrptr_rdclk) begin
      if(rdtoggle==wrtoggle_rdclk) begin
        empty<=1;
      end
    end
end



endmodule

asyncfifotb.v
`include "asyncfifo.v"
`timescale 1ps/1ps
module asyncfifotb();
/*input wrclk,
    input rdclk,
    input [7:0]wrdata,
    input wren,
    input rden,
    input rst,*/
reg wrclk,rdclk,wren,rden,rst;
reg [7:0]wrdata;
/*output reg[7:0]rdata,
    output reg full,
    output reg empty,
    output reg wrerr,
    output reg rderr*/
wire full,empty,wrerr,rderr;
wire [7:0]rdata;
asyncfifo DUT(.wrclk(wrclk),
              .rdclk(rdclk),
              .wren(wren),
              .rden(rden),
              .rst(rst),
              .wrdata(wrdata),
              .full(full),
              .empty(empty),
              .wrerr(wrerr),
              .rderr(rderr),
              .rdata(rdata)
  );
  initial forever begin
    #5 wrclk=~wrclk;
  end
  initial forever begin
    #10 rdclk=~rdclk;
  end
  initial begin
    wren=0;
    rden=0;
    wrclk=0;
    rdclk=0;
    rst=1;
    wrdata=0;
    #15 rst=0;
  end
  initial begin
    #1500 $finish;
  end
  initial begin
    #15;
    repeat(16) begin
      @(posedge wrclk);
      wrdata=$random;
      wren=1;
    end
    @(posedge wrclk);
    wren=0;
    repeat(16) begin
      @(posedge rdclk);
      rden=1;
    end
    @(posedge rdclk);
    rden=0;
  end
  initial begin
    $dumpvars;
    $dumpfile("asyncfifo.vcd");
    $monitor("Time=%t,rst=%b,wrdata=%d,wren=%b,rden=%b,rdata=%d",$time,rst,wrdata,wren,rden,rdata);
  end
 
endmodule

dump.vcd
$date
	Wed Jan 31 23:44:14 2024
$end
$version
	Icarus Verilog
$end
$timescale
	1ps
$end
$scope module asyncfifotb $end
$var wire 1 ! wrerr $end
$var wire 1 " rderr $end
$var wire 8 # rdata [7:0] $end
$var wire 1 $ full $end
$var wire 1 % empty $end
$var reg 1 & rdclk $end
$var reg 1 ' rden $end
$var reg 1 ( rst $end
$var reg 1 ) wrclk $end
$var reg 8 * wrdata [7:0] $end
$var reg 1 + wren $end
$scope module DUT $end
$var wire 1 & rdclk $end
$var wire 1 ' rden $end
$var wire 1 ( rst $end
$var wire 1 ) wrclk $end
$var wire 8 , wrdata [7:0] $end
$var wire 1 + wren $end
$var reg 1 % empty $end
$var reg 1 $ full $end
$var reg 8 - rdata [7:0] $end
$var reg 1 " rderr $end
$var reg 4 . rdptr [3:0] $end
$var reg 4 / rdptr_gray [3:0] $end
$var reg 4 0 rdptr_wrclk [3:0] $end
$var reg 1 1 rdtoggle $end
$var reg 1 2 rdtoggle_wrclk $end
$var reg 1 ! wrerr $end
$var reg 4 3 wrptr [3:0] $end
$var reg 4 4 wrptr_gray [3:0] $end
$var reg 4 5 wrptr_rdclk [3:0] $end
$var reg 1 6 wrtoggle $end
$var reg 1 7 wrtoggle_rdclk $end
$var integer 32 8 i [31:0] $end
$upscope $end
$upscope $end
$enddefinitions $end
$comment Show the parameter values. $end
$dumpall
$end
#0
$dumpvars
b10000 8
07
06
b0 5
b0 4
b0 3
02
01
b0 0
b0 /
b0 .
b0 -
b0 ,
0+
b0 *
0)
1(
0'
0&
1%
0$
b0 #
0"
0!
$end
#5
0%
b10000 8
1)
#10
0)
1&
#15
1%
b1 3
1+
b100100 *
b100100 ,
1)
0(
#20
0)
0&
#25
1%
b1 4
b10 3
b10000001 *
b10000001 ,
1)
#30
0%
b1 5
0)
1&
#35
b11 4
b11 3
b1001 *
b1001 ,
1)
#40
b11 5
0)
0&
#45
b10 4
b100 3
b1100011 *
b1100011 ,
1)
#50
b10 5
0)
1&
#55
b110 4
b101 3
b1101 *
b1101 ,
1)
#60
b110 5
0)
0&
#65
b111 4
b110 3
b10001101 *
b10001101 ,
1)
#70
b111 5
0)
1&
#75
b101 4
b111 3
b1100101 *
b1100101 ,
1)
#80
b101 5
0)
0&
#85
b100 4
b1000 3
b10010 *
b10010 ,
1)
#90
b100 5
0)
1&
#95
b1100 4
b1001 3
b1 *
b1 ,
1)
#100
b1100 5
0)
0&
#105
b1101 4
b1010 3
b1101 *
b1101 ,
1)
#110
b1101 5
0)
1&
#115
b1111 4
b1011 3
b1110110 *
b1110110 ,
1)
#120
b1111 5
0)
0&
#125
b1110 4
b1100 3
b111101 *
b111101 ,
1)
#130
b1110 5
0)
1&
#135
b1010 4
b1101 3
b11101101 *
b11101101 ,
1)
#140
b1010 5
0)
0&
#145
b1011 4
b1110 3
b10001100 *
b10001100 ,
1)
#150
b1011 5
0)
1&
#155
b1001 4
b1111 3
b11111001 *
b11111001 ,
1)
#160
b1001 5
0)
0&
#165
1$
b1000 4
b0 3
16
b11000110 *
b11000110 ,
1)
#170
1$
17
b1000 5
0)
1&
#175
0+
1)
#180
0)
0&
#185
1)
#190
1$
b1 .
b100100 #
b100100 -
1'
0)
1&
#195
1)
#200
0)
0&
#205
1)
#210
1$
b1 /
b10 .
b10000001 #
b10000001 -
0)
1&
#215
0$
b1 0
1)
#220
0)
0&
#225
1)
#230
b11 /
b11 .
b1001 #
b1001 -
0)
1&
#235
b11 0
1)
#240
0)
0&
#245
1)
#250
b10 /
b100 .
b1100011 #
b1100011 -
0)
1&
#255
b10 0
1)
#260
0)
0&
#265
1)
#270
b110 /
b101 .
b1101 #
b1101 -
0)
1&
#275
b110 0
1)
#280
0)
0&
#285
1)
#290
b111 /
b110 .
b10001101 #
b10001101 -
0)
1&
#295
b111 0
1)
#300
0)
0&
#305
1)
#310
b101 /
b111 .
b1100101 #
b1100101 -
0)
1&
#315
b101 0
1)
#320
0)
0&
#325
1)
#330
b100 /
b1000 .
b10010 #
b10010 -
0)
1&
#335
b100 0
1)
#340
0)
0&
#345
1)
#350
b1100 /
b1001 .
b1 #
b1 -
0)
1&
#355
b1100 0
1)
#360
0)
0&
#365
1)
#370
b1101 /
b1010 .
b1101 #
b1101 -
0)
1&
#375
b1101 0
1)
#380
0)
0&
#385
1)
#390
b1111 /
b1011 .
b1110110 #
b1110110 -
0)
1&
#395
b1111 0
1)
#400
0)
0&
#405
1)
#410
b1110 /
b1100 .
b111101 #
b111101 -
0)
1&
#415
b1110 0
1)
#420
0)
0&
#425
1)
#430
b1010 /
b1101 .
b11101101 #
b11101101 -
0)
1&
#435
b1010 0
1)
#440
0)
0&
#445
1)
#450
b1011 /
b1110 .
b10001100 #
b10001100 -
0)
1&
#455
b1011 0
1)
#460
0)
0&
#465
1)
#470
b1001 /
b1111 .
b11111001 #
b11111001 -
0)
1&
#475
b1001 0
1)
#480
0)
0&
#485
1)
#490
12
b1000 /
b0 .
b11000110 #
b11000110 -
11
0)
1&
#495
b1000 0
1)
#500
0)
0&
#505
1)
#510
0'
0)
1&
